smilepack/__init__.py
smilepack/application.py
smilepack/database.py
smilepack/manage.py
smilepack/manifest.json
smilepack/models.py
smilepack/schemas.py
smilepack/settings.py
smilepack/bl/__init__.py
smilepack/bl/icon.py
smilepack/bl/registry.py
smilepack/bl/smilepacks.py
smilepack/bl/smiles.py
smilepack/bl/users.py
smilepack/bl/utils.py
smilepack/public/action-add.6fd2c233.png
smilepack/public/action-delete.9bb9c06c.png
smilepack/public/action-edit.eb5c76d6.png
smilepack/public/action-saved.4d6f55a3.png
smilepack/public/admin_css.10c7b7bc.css
smilepack/public/admin_css.10c7b7bc.js
smilepack/public/admin_js.10c7b7bc.js
smilepack/public/background.880982d0.jpg
smilepack/public/base_css.10c7b7bc.css
smilepack/public/base_css.10c7b7bc.js
smilepack/public/derpy403.5266c46a.png
smilepack/public/derpy404.96fbad11.png
smilepack/public/derpy500.8e77b753.png
smilepack/public/generator_css.10c7b7bc.css
smilepack/public/generator_css.10c7b7bc.js
smilepack/public/generator_js.10c7b7bc.js
smilepack/public/landing_css.10c7b7bc.css
smilepack/public/landing_css.10c7b7bc.js
smilepack/public/landing_js.10c7b7bc.js
smilepack/public/loading.8efca98d.gif
smilepack/public/simplepage_css.10c7b7bc.css
smilepack/public/simplepage_css.10c7b7bc.js
smilepack/public/viewer_js.10c7b7bc.js
smilepack/public/widget_collection_css.10c7b7bc.css
smilepack/public/widget_collection_css.10c7b7bc.js
smilepack/templates/admin.html
smilepack/templates/generator.html
smilepack/templates/index.html
smilepack/templates/login.html
smilepack/templates/robots.txt
smilepack/templates/settings.html
smilepack/templates/simple_page.html
smilepack/templates/sitemap.xml
smilepack/templates/smilepack_classic.meta.js
smilepack/templates/smilepack_classic.user.js
smilepack/templates/view.html
smilepack/templates/errors/403.html
smilepack/templates/errors/404.html
smilepack/templates/errors/500.html
smilepack/translations/ru/LC_MESSAGES/messages.mo
smilepack-0.2.1.dist-info/DESCRIPTION.rst
smilepack-0.2.1.dist-info/METADATA
smilepack-0.2.1.dist-info/RECORD
smilepack-0.2.1.dist-info/WHEEL
smilepack-0.2.1.dist-info/entry_points.txt
smilepack-0.2.1.dist-info/metadata.json
smilepack-0.2.1.dist-info/top_level.txt
