Metadata-Version: 2.0
Name: smilepack
Version: 0.2.1
Summary: A website where you can create collections on smiles and use it on other sites
Home-page: https://bitbucket.org/andreymal/smilepack
Author: andreymal
Author-email: andriyano-31@mail.ru
License: MIT
Platform: linux
Platform: osx
Platform: bsd
Classifier: Development Status :: 4 - Beta
Classifier: Framework :: Flask
Classifier: License :: OSI Approved :: MIT License
Classifier: Operating System :: OS Independent
Classifier: Programming Language :: Python
Classifier: Programming Language :: Python :: 3
Classifier: Programming Language :: Python :: 3.3
Classifier: Programming Language :: Python :: 3.4
Classifier: Programming Language :: Python :: 3.5
Classifier: Topic :: Internet :: WWW/HTTP :: WSGI
Classifier: Topic :: Internet :: WWW/HTTP :: WSGI :: Application
Requires-Dist: Flask
Requires-Dist: Flask-Babel
Requires-Dist: Flask-Limiter
Requires-Dist: Flask-Login
Requires-Dist: Flask-Script
Requires-Dist: Flask-Webpack
Requires-Dist: jsonschema
Requires-Dist: mysqlclient
Requires-Dist: pony (>=0.6.4)
Requires-Dist: pymemcache
Requires-Dist: python3-memcached
Requires-Dist: pytz
Requires-Dist: scrypt
Provides-Extra: imgur
Requires-Dist: Flask-Imgur; extra == 'imgur'
Requires-Dist: Pillow; extra == 'imgur'
